xdj_utils/__init__.py
xdj_utils/authentications.py
xdj_utils/backends.py
xdj_utils/core_initialize.py
xdj_utils/exception.py
xdj_utils/filters.py
xdj_utils/git_utils.py
xdj_utils/json_response.py
xdj_utils/middleware.py
xdj_utils/models.py
xdj_utils/pagination.py
xdj_utils/permission.py
xdj_utils/request_util.py
xdj_utils/serializers.py
xdj_utils/string_util.py
xdj_utils/swagger.py
xdj_utils/validator.py
xdj_utils/viewset.py
xdj_utils-0.0.6.dist-info/LICENSE
xdj_utils-0.0.6.dist-info/METADATA
xdj_utils-0.0.6.dist-info/WHEEL
xdj_utils-0.0.6.dist-info/top_level.txt
xdj_utils-0.0.6.dist-info/RECORD
